python_pydantic/__init__.py
python_pydantic/api_client.py
python_pydantic/api_response.py
python_pydantic/apis/__init__.py
python_pydantic/apis/path_to_api.py
python_pydantic/apis/paths/__init__.py
python_pydantic/apis/paths/reserved_word.py
python_pydantic/apis/paths/simple_endpoint.py
python_pydantic/apis/tag_to_api.py
python_pydantic/apis/tags/__init__.py
python_pydantic/apis/tags/test_api.py
python_pydantic/apis/tags/test_api_raw.py
python_pydantic/client.py
python_pydantic/client.pyi
python_pydantic/client_custom.py
python_pydantic/configuration.py
python_pydantic/exceptions.py
python_pydantic/exceptions_base.py
python_pydantic/model/__init__.py
python_pydantic/model/test_fetch400_response.py
python_pydantic/model/test_fetch400_response.pyi
python_pydantic/model/test_fetch500_response.py
python_pydantic/model/test_fetch500_response.pyi
python_pydantic/model/test_fetch_response.py
python_pydantic/model/test_fetch_response.pyi
python_pydantic/model/test_reserved_word.py
python_pydantic/model/test_reserved_word.pyi
python_pydantic/models/__init__.py
python_pydantic/paths/__init__.py
python_pydantic/paths/reserved_word/__init__.py
python_pydantic/paths/reserved_word/get.py
python_pydantic/paths/reserved_word/get.pyi
python_pydantic/paths/simple_endpoint/__init__.py
python_pydantic/paths/simple_endpoint/get.py
python_pydantic/paths/simple_endpoint/get.pyi
python_pydantic/pydantic/__init__.py
python_pydantic/pydantic/test_fetch400_response.py
python_pydantic/pydantic/test_fetch500_response.py
python_pydantic/pydantic/test_fetch_response.py
python_pydantic/pydantic/test_reserved_word.py
python_pydantic/request_after_hook.py
python_pydantic/request_before_hook.py
python_pydantic/request_before_url_hook.py
python_pydantic/rest.py
python_pydantic/schemas.py
python_pydantic/type/__init__.py
python_pydantic/type/test_fetch400_response.py
python_pydantic/type/test_fetch500_response.py
python_pydantic/type/test_fetch_response.py
python_pydantic/type/test_reserved_word.py
python_pydantic_responses_python_sdk-1.0.0.dist-info/LICENSE
python_pydantic_responses_python_sdk-1.0.0.dist-info/METADATA
python_pydantic_responses_python_sdk-1.0.0.dist-info/WHEEL
python_pydantic_responses_python_sdk-1.0.0.dist-info/RECORD
